{
  "best_model": "Logistic Regression",
  "features": [
    "deal_value_log",
    "months_to_election",
    "months_after_election",
    "time_to_close_or_cancel",
    "market_volatility_proxy",
    "interest_rate_proxy",
    "antitrust_risk_proxy",
    "industry",
    "sector",
    "payment_method",
    "regulatory_review",
    "election_year",
    "transition_year",
    "new_president_year",
    "cross_border_deal",
    "public_target",
    "public_acquirer",
    "rumor_or_leak_indicator"
  ],
  "target": "deal_completed",
  "n_train": 4000,
  "n_test": 1000,
  "class_balance_completed": 0.6582,
  "test_metrics": {
    "model": "Logistic Regression",
    "cv_roc_auc_mean": 0.8647481866033153,
    "cv_roc_auc_std": 0.013330250273713927,
    "test_accuracy": 0.799,
    "test_precision": 0.8840336134453781,
    "test_recall": 0.7993920972644377,
    "test_f1": 0.839584996009577,
    "test_roc_auc": 0.879037131836684
  },
  "test_index": [
    161,
    1051,
    2487,
    1250,
    4217,
    938,
    4323,
    179,
    1602,
    3277,
    2170,
    1304,
    2565,
    4762,
    1274,
    3943,
    1148,
    1957,
    1271,
    4133,
    4370,
    4495,
    816,
    4594,
    4326,
    2116,
    3825,
    4324,
    2980,
    2120,
    2586,
    4250,
    4826,
    2451,
    3055,
    743,
    1040,
    4584,
    3137,
    985,
    3059,
    4577,
    4037,
    791,
    579,
    4139,
    2239,
    1092,
    2851,
    552,
    1894,
    2417,
    1120,
    4392,
    3813,
    3720,
    4894,
    1453,
    2429,
    1743,
    432,
    1858,
    4933,
    2317,
    4632,
    1133,
    2843,
    3528,
    1167,
    4726,
    4355,
    522,
    3342,
    4953,
    3372,
    4813,
    2003,
    3688,
    2840,
    538,
    827,
    405,
    4751,
    2227,
    1402,
    4921,
    4081,
    253,
    2910,
    3678,
    2587,
    569,
    3771,
    46,
    2069,
    4940,
    2004,
    1515,
    4150,
    1077,
    632,
    2384,
    2724,
    4649,
    4424,
    3731,
    591,
    4260,
    1501,
    4345,
    611,
    3155,
    52,
    4009,
    424,
    53,
    2916,
    800,
    1570,
    3923,
    2757,
    4545,
    2254,
    3410,
    1052,
    3370,
    2283,
    4683,
    4477,
    2214,
    3327,
    2551,
    416,
    4483,
    806,
    4101,
    4873,
    4665,
    3611,
    2582,
    3887,
    224,
    4636,
    1,
    3129,
    4135,
    4302,
    3936,
    1785,
    532,
    1404,
    1108,
    3081,
    185,
    491,
    1893,
    69,
    2605,
    4944,
    1483,
    1363,
    3728,
    365,
    2957,
    746,
    294,
    4352,
    1599,
    4221,
    426,
    4244,
    582,
    263,
    1935,
    2194,
    3989,
    3563,
    2076,
    4740,
    4758,
    1781,
    309,
    3748,
    3488,
    2250,
    920,
    2552,
    1997,
    1522,
    1016,
    732,
    3606,
    3946,
    4540,
    2488,
    1765,
    3368,
    4030,
    627,
    1504,
    3236,
    4569,
    1769,
    286,
    4093,
    523,
    3306,
    4317,
    4452,
    4505,
    3896,
    4702,
    819,
    1938,
    2484,
    3752,
    1677,
    1944,
    3056,
    996,
    2024,
    2075,
    2127,
    1654,
    4556,
    623,
    3240,
    4772,
    2868,
    2231,
    3835,
    469,
    759,
    277,
    1805,
    1715,
    4294,
    1618,
    459,
    4225,
    378,
    2106,
    1718,
    872,
    2665,
    559,
    4942,
    3275,
    2830,
    3005,
    748,
    2166,
    4996,
    987,
    1542,
    588,
    1118,
    4660,
    4401,
    3833,
    32,
    4588,
    3694,
    578,
    1233,
    576,
    466,
    3949,
    3315,
    404,
    56,
    4581,
    1607,
    543,
    401,
    2482,
    2788,
    3610,
    2238,
    4456,
    2137,
    698,
    4368,
    201,
    4019,
    3448,
    3012,
    1330,
    879,
    4858,
    917,
    231,
    3587,
    1398,
    3479,
    3252,
    62,
    1314,
    1531,
    2241,
    243,
    2778,
    4535,
    2204,
    4097,
    2717,
    82,
    4151,
    3108,
    2236,
    3430,
    1742,
    2772,
    2909,
    3725,
    2339,
    3821,
    178,
    3894,
    3570,
    4231,
    3693,
    473,
    2569,
    798,
    3746,
    875,
    2929,
    154,
    1969,
    4988,
    4779,
    2896,
    2846,
    3392,
    1672,
    1611,
    1645,
    2315,
    3859,
    2782,
    30,
    4393,
    2561,
    3743,
    4156,
    4380,
    4835,
    2507,
    822,
    3274,
    3079,
    2124,
    2036,
    2222,
    218,
    1662,
    2060,
    1948,
    4678,
    3634,
    2495,
    4034,
    1071,
    3266,
    1961,
    2937,
    3958,
    3660,
    4074,
    4670,
    4044,
    4651,
    3143,
    3045,
    3845,
    1596,
    2071,
    1115,
    2812,
    3272,
    2617,
    38,
    4551,
    2055,
    3642,
    4618,
    2509,
    2260,
    4181,
    3727,
    484,
    797,
    922,
    2247,
    4084,
    1690,
    2431,
    548,
    2165,
    1086,
    377,
    4146,
    3522,
    716,
    337,
    4611,
    3822,
    757,
    775,
    2884,
    619,
    4389,
    3643,
    1030,
    3909,
    2267,
    689,
    2049,
    100,
    3259,
    2629,
    3732,
    3954,
    1286,
    7,
    4610,
    3900,
    1437,
    4038,
    2400,
    4927,
    1528,
    3615,
    4582,
    2801,
    21,
    1263,
    4029,
    2403,
    4069,
    4943,
    4991,
    4162,
    423,
    441,
    2182,
    4275,
    1666,
    2607,
    1545,
    2859,
    2088,
    671,
    411,
    1484,
    4624,
    4804,
    1182,
    2099,
    114,
    1612,
    4399,
    1885,
    4919,
    1740,
    1820,
    1196,
    374,
    2319,
    2176,
    16,
    1764,
    4301,
    2766,
    3416,
    1955,
    1887,
    3379,
    1984,
    2169,
    1380,
    4411,
    3452,
    2711,
    1110,
    1738,
    2061,
    4089,
    1563,
    4519,
    3913,
    534,
    472,
    2687,
    4300,
    3754,
    14,
    717,
    1745,
    4179,
    4648,
    908,
    4170,
    3317,
    4141,
    2895,
    340,
    4299,
    4241,
    2753,
    1521,
    2163,
    2157,
    170,
    4715,
    2633,
    2873,
    3823,
    136,
    1346,
    2273,
    2123,
    125,
    2158,
    4059,
    3353,
    338,
    710,
    4242,
    1588,
    1101,
    3991,
    451,
    4875,
    483,
    3655,
    2964,
    244,
    4795,
    2489,
    3447,
    330,
    4449,
    2559,
    1174,
    2922,
    1549,
    1616,
    3071,
    4263,
    1144,
    4268,
    3166,
    1358,
    131,
    3589,
    2282,
    1083,
    4142,
    2017,
    1365,
    1798,
    4680,
    2992,
    564,
    1386,
    2479,
    3917,
    4578,
    898,
    1295,
    4818,
    1819,
    3816,
    4024,
    4508,
    808,
    1770,
    3132,
    455,
    763,
    644,
    3770,
    4853,
    1113,
    2079,
    3978,
    87,
    1973,
    4808,
    3021,
    2792,
    4511,
    4833,
    2360,
    666,
    1535,
    1464,
    3088,
    500,
    1491,
    1499,
    1248,
    3320,
    1513,
    4565,
    3094,
    696,
    2668,
    4600,
    3915,
    1939,
    3066,
    2476,
    4433,
    4518,
    1308,
    4240,
    991,
    2604,
    1930,
    1100,
    4970,
    3591,
    2366,
    1581,
    2442,
    72,
    4451,
    544,
    3178,
    4311,
    4553,
    2446,
    475,
    2962,
    1992,
    94,
    2990,
    4076,
    3481,
    4108,
    4116,
    3786,
    1236,
    3097,
    65,
    1608,
    2732,
    4614,
    3475,
    3061,
    531,
    1262,
    3834,
    1701,
    4077,
    3100,
    4264,
    2600,
    4481,
    959,
    2714,
    4538,
    3147,
    1995,
    4406,
    1810,
    4444,
    2677,
    4230,
    625,
    3050,
    1768,
    730,
    2081,
    4637,
    921,
    4529,
    4905,
    4929,
    2761,
    4507,
    2168,
    283,
    3227,
    4008,
    1323,
    4493,
    4681,
    1780,
    2635,
    2353,
    1087,
    2744,
    2270,
    3778,
    202,
    1254,
    3656,
    530,
    1203,
    4409,
    2070,
    4216,
    2242,
    1388,
    1074,
    3052,
    682,
    2305,
    1109,
    1517,
    3224,
    2364,
    3712,
    801,
    3263,
    3509,
    1814,
    2358,
    2133,
    3626,
    566,
    2463,
    4760,
    2028,
    3886,
    1085,
    615,
    101,
    2975,
    4314,
    2540,
    4868,
    1926,
    3015,
    1107,
    1223,
    4234,
    2888,
    1519,
    1220,
    3781,
    4563,
    4640,
    1870,
    810,
    2808,
    4963,
    2094,
    4414,
    3023,
    463,
    4360,
    4474,
    2648,
    3920,
    1410,
    2050,
    3321,
    3988,
    1638,
    2630,
    3883,
    1879,
    3058,
    22,
    947,
    412,
    4232,
    4797,
    1520,
    2443,
    2594,
    3164,
    4937,
    4475,
    2216,
    3181,
    758,
    4522,
    1732,
    433,
    3585,
    2710,
    3025,
    4899,
    1883,
    3601,
    2557,
    2156,
    1633,
    2402,
    1703,
    966,
    3613,
    228,
    637,
    1487,
    3621,
    71,
    3719,
    45,
    4724,
    4359,
    1707,
    1445,
    2454,
    3625,
    2809,
    4547,
    4843,
    1943,
    4331,
    4419,
    2424,
    1258,
    3779,
    1726,
    4303,
    407,
    4825,
    2759,
    4659,
    28,
    4671,
    1187,
    2626,
    3957,
    864,
    2758,
    3095,
    4909,
    3409,
    1419,
    1590,
    1067,
    4177,
    369,
    518,
    1416,
    2096,
    1614,
    924,
    2464,
    3356,
    2109,
    3383,
    516,
    4738,
    4028,
    2746,
    2971,
    4487,
    1443,
    2285,
    1072,
    2392,
    1847,
    1999,
    468,
    2878,
    4208,
    3319,
    2745,
    1122,
    1986,
    2588,
    2660,
    786,
    1876,
    207,
    4107,
    3730,
    3438,
    2134,
    3582,
    2968,
    912,
    4752,
    4661,
    4771,
    250,
    3031,
    3003,
    3596,
    1569,
    3364,
    3096,
    2010,
    2149,
    2770,
    434,
    120,
    251,
    643,
    1000,
    1259,
    1428,
    3225,
    2805,
    3289,
    126,
    610,
    897,
    4841,
    3614,
    1241,
    4759,
    2527,
    4605,
    3177,
    3035,
    580,
    3622,
    4438,
    2018,
    1037,
    4164,
    3581,
    711,
    2237,
    196,
    4492,
    4832,
    1446,
    3506,
    4513,
    821,
    1121,
    4270,
    4597,
    3085,
    4642,
    957,
    1440,
    2531,
    4086,
    4918,
    4445,
    1850,
    1049,
    2662,
    387,
    2514,
    3312,
    4186,
    4434,
    1897,
    4765,
    4131,
    1327,
    856,
    3159,
    1384,
    4035,
    3127,
    3874,
    3393,
    3651,
    3498,
    697,
    3782,
    3347,
    4701,
    156,
    3007,
    2556,
    2418,
    324,
    1272,
    1927,
    3286,
    1779,
    2902,
    3276,
    3298,
    1257,
    4073,
    4412,
    4339,
    1717,
    4675,
    1566,
    310,
    2053,
    2121,
    2959,
    3332,
    4175,
    4372,
    3070,
    4907,
    3673,
    2612,
    946,
    2893,
    4308
  ]
}